asyncio_addon/__init__.py
asyncio_addon/decorator.py
asyncio_addon/sync.py
asyncio_addon/task.py
asyncio_addon/task_group.py
asyncio_addon-0.3.0.dist-info/METADATA
asyncio_addon-0.3.0.dist-info/WHEEL
asyncio_addon-0.3.0.dist-info/RECORD
