Metadata-Version: 2.4
Name: asyncio-addon
Version: 0.3.0
Summary: Some convenient utilities for asyncio
Project-URL: Repository, https://github.com/observerw/asyncio-addon
Author-email: observerw <wozluohd@gmail.com>
Keywords: asyncio
Classifier: Programming Language :: Python
Classifier: Programming Language :: Python :: 3.11
Classifier: Programming Language :: Python :: 3.12
Classifier: Programming Language :: Python :: 3.13
Requires-Python: >=3.11
